<annotation>
	<folder></folder>
	<filename>second_rehkitze4383_jpg.rf.728c9ea3f45ae82ce7ec3fddfeaba296.jpg</filename>
	<path>second_rehkitze4383_jpg.rf.728c9ea3f45ae82ce7ec3fddfeaba296.jpg</path>
	<source>
		<database>roboflow.ai</database>
	</source>
	<size>
		<width>416</width>
		<height>416</height>
		<depth>3</depth>
	</size>
	<segmented>0</segmented>
	<object>
		<name>rehkitze</name>
		<pose>Unspecified</pose>
		<truncated>0</truncated>
		<difficult>0</difficult>
		<occluded>0</occluded>
		<bndbox>
			<xmin>222</xmin>
			<xmax>241</xmax>
			<ymin>148</ymin>
			<ymax>197</ymax>
		</bndbox>
	</object>
	<object>
		<name>rehkitze</name>
		<pose>Unspecified</pose>
		<truncated>0</truncated>
		<difficult>0</difficult>
		<occluded>0</occluded>
		<bndbox>
			<xmin>291</xmin>
			<xmax>339</xmax>
			<ymin>177</ymin>
			<ymax>235</ymax>
		</bndbox>
	</object>
</annotation>
